{"openapi":"3.0.1","info":{"title":"RBAC GO API","description":"This is a RBAC server.","contact":{},"version":"1.0"},"servers":[{"url":"/"}],"paths":{"/account":{"post":{"tags":["Account"],"summary":"User 생성","requestBody":{"description":"회원가입 정보","content":{"application/json":{"schema":{"$ref":"#/components/schemas/models.AddUserData"}}},"required":true},"responses":{"200":{"description":"OK","content":{"application/json":{"schema":{"$ref":"#/components/schemas/models.LoginResult"}}}}},"x-codegen-request-body-name":"data"}},"/account/login":{"post":{"tags":["Account"],"summary":"로그인","requestBody":{"description":"로그인 정보","content":{"application/json":{"schema":{"$ref":"#/components/schemas/models.LoginRequest"}}},"required":true},"responses":{"200":{"description":"access token & refresh token","content":{"application/json":{"schema":{"$ref":"#/components/schemas/models.LoginResult"}}}}},"x-codegen-request-body-name":"data"}},"/account/name/list":{"post":{"tags":["Account"],"summary":"사용자 이름 목록 조회","requestBody":{"description":"Data","content":{"application/json":{"schema":{"$ref":"#/components/schemas/rest.UserIDList"}}},"required":true},"responses":{"200":{"description":"OK","content":{"application/json":{"schema":{"$ref":"#/components/schemas/dblayer.UserIDName"}}}}},"x-codegen-request-body-name":"data"}},"/account/renew":{"post":{"tags":["Account"],"summary":"access token 재발급","requestBody":{"description":"Refresh Token","content":{"application/json":{"schema":{"$ref":"#/components/schemas/rest.refreshToken"}}},"required":true},"responses":{"200":{"description":"access token","content":{"application/json":{"schema":{"type":"string"}}}}},"x-codegen-request-body-name":"data"}},"/account/valid":{"post":{"tags":["Account"],"summary":"access token 인증","requestBody":{"description":"Access Token","content":{"application/json":{"schema":{"$ref":"#/components/schemas/rest.accessToken"}}},"required":true},"responses":{"200":{"description":"유효성 검증 결과","content":{"application/json":{"schema":{"type":"boolean"}}}}},"x-codegen-request-body-name":"data"}},"/content":{"post":{"tags":["Content"],"summary":"Content 생성","requestBody":{"description":"Content Data","content":{"application/json":{"schema":{"$ref":"#/components/schemas/models.ContentData"}}},"required":true},"responses":{"200":{"description":"OK","content":{"application/json":{"schema":{"$ref":"#/components/schemas/models.Content"}}}}},"x-codegen-request-body-name":"data"}},"/content/list":{"get":{"tags":["Content"],"summary":"Content 목록 조회","description":"Content 목록 조회","parameters":[{"name":"page","in":"query","description":"Page Number","schema":{"type":"integer"}},{"name":"pageSize","in":"query","description":"Page Size","schema":{"type":"integer"}}],"responses":{"200":{"description":"OK","content":{"application/json":{"schema":{"$ref":"#/components/schemas/models.ContentList"}}}}}}},"/content/{id}":{"get":{"tags":["Content"],"summary":"Content 상세 조회","description":"Content 상세 조회","parameters":[{"name":"id","in":"path","description":"Content id","required":true,"schema":{"type":"integer"}}],"responses":{"200":{"description":"OK","content":{"application/json":{"schema":{"$ref":"#/components/schemas/models.Content"}}}}}},"delete":{"tags":["Content"],"summary":"Content 삭제","parameters":[{"name":"id","in":"path","description":"Content id","required":true,"schema":{"type":"integer"}}],"responses":{"200":{"description":"OK","content":{"application/json":{"schema":{"$ref":"#/components/schemas/models.Content"}}}}}},"patch":{"tags":["Content"],"summary":"Content 수정","parameters":[{"name":"id","in":"path","description":"Content id","required":true,"schema":{"type":"integer"}}],"requestBody":{"description":"Content Data","content":{"application/json":{"schema":{"$ref":"#/components/schemas/models.ContentData"}}},"required":true},"responses":{"200":{"description":"OK","content":{"application/json":{"schema":{"$ref":"#/components/schemas/models.Content"}}}}},"x-codegen-request-body-name":"data"}},"/rbac/permission":{"post":{"tags":["RBAC permission"],"summary":"Permission 생성","requestBody":{"description":"Data","content":{"application/json":{"schema":{"$ref":"#/components/schemas/dblayer.PermissionData"}}},"required":true},"responses":{"200":{"description":"OK","content":{"application/json":{"schema":{"$ref":"#/components/schemas/models.Permission"}}}}},"x-codegen-request-body-name":"data"}},"/rbac/permission-assignment":{"post":{"tags":["RBAC permissionAssignment"],"summary":"PermissionAssignment 생성","requestBody":{"description":"Data","content":{"application/json":{"schema":{"$ref":"#/components/schemas/dblayer.PermissionAssignmentData"}}},"required":true},"responses":{"200":{"description":"OK","content":{"application/json":{"schema":{"$ref":"#/components/schemas/models.PermissionAssignment"}}}}},"x-codegen-request-body-name":"data"},"delete":{"tags":["RBAC permissionAssignment"],"summary":"PermissionAssignment 삭제","parameters":[{"name":"permissionID","in":"query","description":"permission id","required":true,"schema":{"type":"integer"}},{"name":"roleID","in":"query","description":"role id","required":true,"schema":{"type":"integer"}}],"responses":{"200":{"description":"삭제된 PermissionAssignment 데이터","content":{"application/json":{"schema":{"$ref":"#/components/schemas/models.PermissionAssignment"}}}}}}},"/rbac/permission/list":{"get":{"tags":["RBAC permission"],"summary":"Permission 목록 조회","parameters":[{"name":"page","in":"query","description":"Page Number","schema":{"type":"integer"}},{"name":"pageSize","in":"query","description":"Page Size","schema":{"type":"integer"}}],"responses":{"200":{"description":"OK","content":{"application/json":{"schema":{"$ref":"#/components/schemas/dblayer.PermissionsPage"}}}}}}},"/rbac/permission/objects":{"post":{"tags":["RBAC permission"],"summary":"Permission 에 해당하는 objects 조회","requestBody":{"description":"Object를 구하는데 필요한 permission 정보","content":{"application/json":{"schema":{"$ref":"#/components/schemas/rest.PermissionQuery"}}},"required":true},"responses":{"200":{"description":"허용된 object list","content":{"application/json":{"schema":{"$ref":"#/components/schemas/dblayer.PermissionAnswer"}}}}},"x-codegen-request-body-name":"data"}},"/rbac/permission/set":{"post":{"tags":["RBAC permission"],"summary":"Permission Set 생성 및 동기화","requestBody":{"description":"Data","content":{"application/json":{"schema":{"$ref":"#/components/schemas/dblayer.PermissionSetData"}}},"required":true},"responses":{"200":{"description":"OK","content":{"application/json":{"schema":{"type":"array","items":{"$ref":"#/components/schemas/models.Permission"}}}}}},"x-codegen-request-body-name":"data"}},"/rbac/permission/{id}":{"delete":{"tags":["RBAC permission"],"summary":"Permission 삭제","parameters":[{"name":"id","in":"path","description":"Permission ID","required":true,"schema":{"type":"integer"}}],"responses":{"200":{"description":"삭제된 Permission 데이터","content":{"application/json":{"schema":{"$ref":"#/components/schemas/models.Permission"}}}}}},"patch":{"tags":["RBAC permission"],"summary":"Permission Update","parameters":[{"name":"id","in":"path","description":"Permission ID","required":true,"schema":{"type":"integer"}}],"requestBody":{"description":"Update에 사용할 Data","content":{"application/json":{"schema":{"$ref":"#/components/schemas/dblayer.PermissionData"}}},"required":true},"responses":{"200":{"description":"수정된 Permission 데이터","content":{"application/json":{"schema":{"$ref":"#/components/schemas/models.Permission"}}}}},"x-codegen-request-body-name":"data"}},"/rbac/role":{"post":{"tags":["RBAC role"],"summary":"Role 생성","requestBody":{"description":"Data","content":{"application/json":{"schema":{"$ref":"#/components/schemas/dblayer.RoleData"}}},"required":true},"responses":{"200":{"description":"OK","content":{"application/json":{"schema":{"$ref":"#/components/schemas/models.Role"}}}}},"x-codegen-request-body-name":"data"}},"/rbac/role/list":{"get":{"tags":["RBAC role"],"summary":"Role 목록 조회","parameters":[{"name":"page","in":"query","description":"Page Number","schema":{"type":"integer"}},{"name":"pageSize","in":"query","description":"Page Size","schema":{"type":"integer"}}],"responses":{"200":{"description":"OK","content":{"application/json":{"schema":{"$ref":"#/components/schemas/dblayer.RolesPage"}}}}}}},"/rbac/role/{id}":{"delete":{"tags":["RBAC role"],"summary":"Role 삭제","parameters":[{"name":"id","in":"path","description":"Role ID","required":true,"schema":{"type":"integer"}}],"responses":{"200":{"description":"삭제된 Role 데이터","content":{"application/json":{"schema":{"$ref":"#/components/schemas/models.Role"}}}}}},"patch":{"tags":["RBAC role"],"summary":"Role Update","parameters":[{"name":"id","in":"path","description":"Role ID","required":true,"schema":{"type":"integer"}}],"requestBody":{"description":"Update에 사용할 Data","content":{"application/json":{"schema":{"$ref":"#/components/schemas/dblayer.RoleData"}}},"required":true},"responses":{"200":{"description":"수정된 Role 데이터","content":{"application/json":{"schema":{"$ref":"#/components/schemas/models.Role"}}}}},"x-codegen-request-body-name":"data"}},"/rbac/role/{id}/permission":{"get":{"tags":["RBAC role"],"summary":"특정 Role Permission 목록 조회","parameters":[{"name":"id","in":"path","description":"Role ID","required":true,"schema":{"type":"integer"}},{"name":"page","in":"query","description":"Page Number","schema":{"type":"integer"}},{"name":"pageSize","in":"query","description":"Page Size","schema":{"type":"integer"}}],"responses":{"200":{"description":"OK","content":{"application/json":{"schema":{"$ref":"#/components/schemas/dblayer.PermissionsPage"}}}}}}},"/rbac/role/{id}/subject":{"get":{"tags":["RBAC role"],"summary":"특정 Role Subject 목록 조회","parameters":[{"name":"id","in":"path","description":"Role ID","required":true,"schema":{"type":"integer"}},{"name":"page","in":"query","description":"Page Number","schema":{"type":"integer"}},{"name":"pageSize","in":"query","description":"Page Size","schema":{"type":"integer"}}],"responses":{"200":{"description":"OK","content":{"application/json":{"schema":{"$ref":"#/components/schemas/dblayer.SubjectsStatusPage"}}}}}}},"/rbac/subject-assignment":{"post":{"tags":["RBAC subjectAssignment"],"summary":"SubjectAssignment 생성","requestBody":{"description":"Data","content":{"application/json":{"schema":{"$ref":"#/components/schemas/dblayer.SubjectAssignmentData"}}},"required":true},"responses":{"200":{"description":"OK","content":{"application/json":{"schema":{"$ref":"#/components/schemas/models.SubjectAssignment"}}}}},"x-codegen-request-body-name":"data"},"delete":{"tags":["RBAC subjectAssignment"],"summary":"SubjectAssignment 삭제","requestBody":{"description":"Data","content":{"application/json":{"schema":{"$ref":"#/components/schemas/dblayer.SubjectAssignmentData"}}},"required":true},"responses":{"200":{"description":"삭제된 SubjectAssignment 데이터","content":{"application/json":{"schema":{"$ref":"#/components/schemas/models.SubjectAssignment"}}}}},"x-codegen-request-body-name":"data"}}},"components":{"schemas":{"dblayer.PermissionAnswer":{"type":"object","properties":{"is_allowed":{"type":"boolean"},"objects":{"type":"array","items":{"type":"string"}}}},"dblayer.PermissionAssignmentData":{"type":"object","properties":{"permission_id":{"type":"integer"},"role_id":{"type":"integer"}}},"dblayer.PermissionData":{"type":"object","properties":{"action":{"type":"string"},"name":{"type":"string"},"object":{"type":"string"},"service_name":{"type":"string"}}},"dblayer.PermissionSet":{"type":"object","properties":{"actions":{"type":"array","items":{"type":"string"}},"name":{"type":"string"},"objects":{"type":"array","items":{"type":"string"}}}},"dblayer.PermissionSetData":{"type":"object","properties":{"permission_sets":{"type":"array","items":{"$ref":"#/components/schemas/dblayer.PermissionSet"}},"service_name":{"type":"string"}}},"dblayer.PermissionsPage":{"type":"object","properties":{"count":{"type":"integer"},"next":{"type":"string"},"previous":{"type":"string"},"results":{"type":"array","items":{"$ref":"#/components/schemas/models.Permission"}}}},"dblayer.RoleData":{"type":"object","properties":{"description":{"type":"string"},"name":{"type":"string"}}},"dblayer.RolesPage":{"type":"object","properties":{"count":{"type":"integer"},"next":{"type":"string"},"previous":{"type":"string"},"results":{"type":"array","items":{"$ref":"#/components/schemas/models.Role"}}}},"dblayer.SubjectAssignmentData":{"type":"object","properties":{"role_id":{"type":"integer"},"subject_id":{"type":"integer"}}},"dblayer.SubjectStatus":{"type":"object","properties":{"is_allowed":{"type":"boolean"},"subject_id":{"type":"integer"}}},"dblayer.SubjectsStatusPage":{"type":"object","properties":{"count":{"type":"integer"},"next":{"type":"string"},"previous":{"type":"string"},"results":{"type":"array","items":{"$ref":"#/components/schemas/dblayer.SubjectStatus"}}}},"dblayer.UserIDName":{"type":"object","properties":{"id":{"type":"integer"},"name":{"type":"string"}}},"models.AddUserData":{"required":["login_id","password"],"type":"object","properties":{"email":{"type":"string"},"login_id":{"type":"string"},"name":{"type":"string"},"password":{"type":"string"}}},"models.Content":{"type":"object","properties":{"content":{"type":"string"},"created_at":{"type":"string"},"id":{"type":"integer"},"summary":{"type":"string"},"title":{"type":"string"},"updated_at":{"type":"string"},"user":{"type":"integer"}}},"models.ContentData":{"type":"object","properties":{"content":{"type":"string"},"summary":{"type":"string"},"title":{"type":"string"}}},"models.ContentItem":{"type":"object","properties":{"id":{"type":"integer"},"summary":{"type":"string"},"title":{"type":"string"}}},"models.ContentList":{"type":"object","properties":{"count":{"type":"integer"},"next":{"type":"string"},"previous":{"type":"string"},"results":{"type":"array","items":{"$ref":"#/components/schemas/models.ContentItem"}}}},"models.LoginRequest":{"required":["login_id","password"],"type":"object","properties":{"login_id":{"type":"string"},"password":{"type":"string"}}},"models.LoginResult":{"type":"object","properties":{"access_token":{"type":"string"},"refresh_token":{"type":"string"},"user_id":{"type":"integer"}}},"models.Permission":{"type":"object","properties":{"action":{"type":"string"},"id":{"type":"integer"},"name":{"type":"string"},"object":{"type":"string"},"service_name":{"type":"string"}}},"models.PermissionAssignment":{"type":"object","properties":{"id":{"type":"integer"},"permission_id":{"type":"integer"},"role_id":{"type":"integer"}}},"models.Role":{"type":"object","properties":{"description":{"type":"string"},"id":{"type":"integer"},"name":{"type":"string"}}},"models.SubjectAssignment":{"type":"object","properties":{"id":{"type":"integer"},"role_id":{"type":"integer"},"subject_id":{"type":"integer"}}},"rest.PermissionQuery":{"type":"object","properties":{"action":{"type":"string"},"name":{"type":"string"},"service_name":{"type":"string"},"subject_id":{"type":"integer"}}},"rest.UserIDList":{"type":"object","properties":{"id_list":{"type":"array","items":{"type":"integer"}}}},"rest.accessToken":{"type":"object","properties":{"access_token":{"type":"string"}}},"rest.refreshToken":{"type":"object","properties":{"refresh_token":{"type":"string"}}}}}}